causal_testing/__init__.py
causal_testing/__main__.py
causal_testing/_version.py
causal_testing/main.py
causal_testing/estimation/__init__.py
causal_testing/estimation/abstract_estimator.py
causal_testing/estimation/abstract_regression_estimator.py
causal_testing/estimation/cubic_spline_estimator.py
causal_testing/estimation/effect_estimate.py
causal_testing/estimation/experimental_estimator.py
causal_testing/estimation/genetic_programming_regression_fitter.py
causal_testing/estimation/instrumental_variable_estimator.py
causal_testing/estimation/ipcw_estimator.py
causal_testing/estimation/linear_regression_estimator.py
causal_testing/estimation/logistic_regression_estimator.py
causal_testing/specification/__init__.py
causal_testing/specification/causal_dag.py
causal_testing/specification/scenario.py
causal_testing/specification/variable.py
causal_testing/surrogate/__init__.py
causal_testing/surrogate/causal_surrogate_assisted.py
causal_testing/surrogate/surrogate_search_algorithms.py
causal_testing/testing/__init__.py
causal_testing/testing/base_test_case.py
causal_testing/testing/causal_effect.py
causal_testing/testing/causal_test_adequacy.py
causal_testing/testing/causal_test_case.py
causal_testing/testing/causal_test_result.py
causal_testing/testing/effect.py
causal_testing/testing/intervention.py
causal_testing/testing/metamorphic_relation.py
causal_testing/utils/__init__.py
causal_testing/utils/validation.py
causal_testing_framework-14.0.0.dist-info/licenses/LICENSE
dafni/.dockerignore
dafni/.env
dafni/Dockerfile
dafni/README.md
dafni/docker-compose.yaml
dafni/entrypoint.sh
dafni/model_definition.yaml
dafni/data/inputs/causal-tests/causal_tests.json
dafni/data/inputs/dag-data/dag.dot
dafni/data/inputs/runtime-data/runtime_data.csv
dafni/data/outputs/causal_test_results.json
docs/Makefile
docs/README.md
docs/make.bat
docs/source/background.rst
docs/source/conf.py
docs/source/credits.rst
docs/source/glossary.rst
docs/source/index.rst
docs/source/installation.rst
docs/source/requirements.txt
docs/source/tutorials.rst
causal_testing_framework-14.0.0.dist-info/METADATA
causal_testing_framework-14.0.0.dist-info/WHEEL
causal_testing_framework-14.0.0.dist-info/top_level.txt
causal_testing_framework-14.0.0.dist-info/RECORD
