Metadata-Version: 2.4
Name: causal_testing_framework
Version: 14.0.0
Summary: A framework for causal testing using causal directed acyclic graphs.
Author: The CITCOM team
License: MIT
Project-URL: Homepage, https://sites.google.com/sheffield.ac.uk/citcom/home
Project-URL: Documentation, https://causal-testing-framework.readthedocs.io/
Project-URL: Repository, https://github.com/CITCOM-project/CausalTestingFramework
Project-URL: Issues, https://github.com/CITCOM-project/CausalTestingFramework/issues
Keywords: causal inference,verification
Requires-Python: <3.14,>=3.10
License-File: LICENSE
Requires-Dist: lifelines~=0.30.0
Requires-Dist: networkx<3.5,>=3.4
Requires-Dist: numpy<=2.2.0,>=1.26.0
Requires-Dist: pandas>=2.1
Requires-Dist: scikit_learn~=1.4
Requires-Dist: scipy<=1.16.2,>=1.12.0
Requires-Dist: statsmodels~=0.14
Requires-Dist: tabulate~=0.9
Requires-Dist: pydot~=2.0
Requires-Dist: pygad~=3.3
Requires-Dist: deap~=1.4.1
Requires-Dist: sympy~=1.13.1
Requires-Dist: pyarrow~=19.0.1
Requires-Dist: fastparquet~=2024.11.0
Requires-Dist: tqdm~=4.67.1
Provides-Extra: dev
Requires-Dist: astroid==3.3.8; extra == "dev"
Requires-Dist: isort; extra == "dev"
Requires-Dist: pytest; extra == "dev"
Requires-Dist: pylint; extra == "dev"
Requires-Dist: black; extra == "dev"
Requires-Dist: autoapi; extra == "dev"
Requires-Dist: myst-parser; extra == "dev"
Requires-Dist: sphinx; extra == "dev"
Requires-Dist: sphinx-autoapi; extra == "dev"
Requires-Dist: sphinx_rtd_theme; extra == "dev"
Requires-Dist: nbsphinx; extra == "dev"
Requires-Dist: ipykernel; extra == "dev"
Requires-Dist: pandoc; extra == "dev"
Requires-Dist: pre-commit; extra == "dev"
Requires-Dist: tox; extra == "dev"
Provides-Extra: test
Requires-Dist: nbclient; extra == "test"
Requires-Dist: nbformat; extra == "test"
Requires-Dist: ipykernel; extra == "test"
Dynamic: license-file
